greener_servermock/__init__.py
greener_servermock/iotypes.py
greener_servermock/libgreener_servermock.dylib
greener_servermock/servermock.py
greener_servermock-1.3.0.dist-info/licenses/LICENSE
greener_servermock-1.3.0.dist-info/METADATA
greener_servermock-1.3.0.dist-info/WHEEL
greener_servermock-1.3.0.dist-info/top_level.txt
greener_servermock-1.3.0.dist-info/RECORD
