Metadata-Version: 2.4
Name: greener-servermock
Version: 1.3.0
Summary: Python binding for Greener Servermock
Home-page: https://cephei8.github.io/greener
Author: cephei8
Author-email: 
Classifier: Programming Language :: Python :: 3
Requires-Python: >=3.7, <4
License-File: LICENSE
Requires-Dist: pydantic
Dynamic: author
Dynamic: classifier
Dynamic: home-page
Dynamic: license-file
Dynamic: requires-dist
Dynamic: requires-python
Dynamic: summary
